colabohash/__init__.py
colabohash/exceptions.py
colabohash/unzip.py
colabohash/utils.py
colabohash/bin/chromedriver
colabohash/bin/chromedriver_linux64.zip
colabohash/bin/chromedriver_mac64.zip
colabohash/bin/chromedriver_win32.zip
colabohash/bin/notes.txt
colabohash-0.0.5.dist-info/LICENSE
colabohash-0.0.5.dist-info/METADATA
colabohash-0.0.5.dist-info/WHEEL
colabohash-0.0.5.dist-info/top_level.txt
colabohash-0.0.5.dist-info/RECORD
