Metadata-Version: 2.1
Name: colabohash
Version: 0.0.5
Summary: Hashcat with GPU support in Google Colab runtime
Home-page: http://github.com/apogiatzis/colabohash
Author: Antreas Pogiatzis
Author-email: pogiatzis.c.a@gmail.com
License: MIT
Platform: UNKNOWN
Classifier: Development Status :: 3 - Alpha
Classifier: Intended Audience :: Developers
Classifier: Intended Audience :: Information Technology
Classifier: Topic :: Software Development :: Build Tools
Classifier: License :: OSI Approved :: MIT License
Classifier: Programming Language :: Python :: 3
Classifier: Programming Language :: Python :: 3.4
Classifier: Programming Language :: Python :: 3.5
Classifier: Programming Language :: Python :: 3.6
Classifier: Topic :: Security
Classifier: Topic :: Security :: Cryptography
Requires-Dist: html5lib (==1.1)
Requires-Dist: jinja2 (==2.11.2)
Requires-Dist: markupsafe (==1.1.1)
Requires-Dist: mechanize (==0.4.5)
Requires-Dist: selenium (==3.141.0)
Requires-Dist: six (==1.15.0)
Requires-Dist: urllib3 (==1.25.9)
Requires-Dist: webencodings (==0.5.1)
